open_responses/__init__.py
open_responses/bin/open-responses-linux
open_responses/bin/open-responses-macos
open_responses/bin/open-responses-win.exe
open_responses-0.1.6.dist-info/METADATA
open_responses-0.1.6.dist-info/WHEEL
open_responses-0.1.6.dist-info/entry_points.txt
open_responses-0.1.6.dist-info/licenses/LICENSE
open_responses-0.1.6.dist-info/RECORD
