Metadata-Version: 2.4
Name: open-responses
Version: 0.1.6
Summary: CLI for setting up a self-hosted alternative to OpenAI's Responses API
Project-URL: Repository, https://github.com/julep-ai/open-responses
Project-URL: Issues, https://github.com/julep-ai/open-responses/issues
Author-email: Julep AI <info@example.com>
License: Apache-2.0
License-File: LICENSE
Classifier: License :: OSI Approved :: Apache Software License
Classifier: Operating System :: OS Independent
Classifier: Programming Language :: Python :: 3
Requires-Python: >=3.7
